Metadata-Version: 2.1
Name: django-durationwidget2
Version: 1.0.6
Summary: Django Duration field widget to handle duration field in the form
Home-page: https://github.com/pozzolana93/django-durationwidget
Author: Simone Pozzoli
Author-email: simonepozzoli1@gmail.com
License: UNKNOWN
Platform: UNKNOWN
Classifier: Programming Language :: Python :: 2
Classifier: Programming Language :: Python :: 3
Classifier: License :: OSI Approved :: MIT License
Classifier: Operating System :: OS Independent
Requires-Dist: Django (>=1.11)
